{"mc":{
	"auction_guest1":{
		"frameRate":24,
		"events":[
			
			],
		"frames":[
			
			{
			"res":"1A332B0E",
			"x":9,
			"y":29
			},
			{
			"res":"C46E5723",
			"x":9,
			"y":29
			},
			{
			"res":"DA520BF1",
			"x":9,
			"y":29
			},
			{
			"res":"C8E320FF",
			"x":9,
			"y":29
			},
			{
			"res":"8AE70AA6",
			"x":9,
			"y":21
			},
			{
			"res":"29CE6A0B",
			"x":9,
			"y":10
			},
			{
			"res":"31616ABD",
			"x":9,
			"y":5,
			"duration":15
			},
			{
			"res":"1140921B",
			"x":9,
			"y":14
			},
			{
			"res":"26E830C6",
			"x":9,
			"y":29
			},
			{
			"res":"DA520BF1",
			"x":9,
			"y":29
			}
			]
}},
	"res":{
		"8AE70AA6":{"x":151,"y":0,"w":109,"h":113},
		"C46E5723":{"x":238,"y":253,"w":106,"h":105},
		"31616ABD":{"x":0,"y":0,"w":149,"h":129},
		"26E830C6":{"x":262,"y":0,"w":106,"h":105},
		"C8E320FF":{"x":130,"y":253,"w":106,"h":105},
		"1A332B0E":{"x":0,"y":257,"w":106,"h":105},
		"29CE6A0B":{"x":0,"y":131,"w":128,"h":124},
		"1140921B":{"x":130,"y":131,"w":121,"h":120},
		"DA520BF1":{"x":262,"y":107,"w":106,"h":105}
	}}