{"file":"fhqgt_body2.png","frames":{"fhqgt_07_01_png":{"x":0,"y":0,"w":1339,"h":1492,"offX":0,"offY":0,"sourceW":1339,"sourceH":1492},"fhqgt_09_02_png":{"x":1303,"y":1494,"w":30,"h":106,"offX":0,"offY":0,"sourceW":30,"sourceH":106},"fhqgt_09_03_png":{"x":249,"y":1648,"w":81,"h":119,"offX":0,"offY":0,"sourceW":81,"sourceH":119},"fhqgt_09_04_png":{"x":0,"y":1648,"w":144,"h":136,"offX":0,"offY":0,"sourceW":144,"sourceH":136},"fhqgt_10_01_png":{"x":1341,"y":0,"w":627,"h":1520,"offX":0,"offY":0,"sourceW":627,"sourceH":1520},"fhqgt_08_01_png":{"x":669,"y":1494,"w":498,"h":164,"offX":0,"offY":0,"sourceW":498,"sourceH":164},"fhqgt_08_02_png":{"x":1169,"y":1494,"w":132,"h":157,"offX":0,"offY":0,"sourceW":132,"sourceH":157},"fhqgt_08_03_png":{"x":0,"y":1494,"w":667,"h":152,"offX":0,"offY":0,"sourceW":667,"sourceH":152},"fhqgt_09_01_png":{"x":146,"y":1648,"w":101,"h":128,"offX":0,"offY":0,"sourceW":101,"sourceH":128}}}